{"Verona": {"mentions": 8, "relationships": ["Montague", "ho", "Juliet", "Verona", "Thou", "Cast"]}, "Montague": {"mentions": 18, "relationships": ["Montague", "ho", "Jove", "Juliet", "Romeo", "Verona", "Thou", "Cast"]}, "John": {"mentions": 1, "relationships": ["John"]}, "BENVOLIO": {"mentions": 8, "relationships": ["BENVOLIO"]}, "Benvolio": {"mentions": 6, "relationships": ["Benvolio", "Mercutio", "Romeo"]}, "Montagues": {"mentions": 3, "relationships": ["Montagues", "Juliet"]}, "Citizens": {"mentions": 1, "relationships": ["Citizens"]}, "ho": {"mentions": 12, "relationships": ["Montague", "ho", "dun", "Juliet", "Verona", "Cast"]}, "Old Montague": {"mentions": 1, "relationships": ["Old Montague"]}, "MONTAGUE": {"mentions": 3, "relationships": ["MONTAGUE"]}, "Thou": {"mentions": 11, "relationships": ["Montague", "Shalt", "Hath", "Jove", "Romeo Leap", "Depart", "Juliet", "Gallop", "Verona", "Thou", "Phaethon"]}, "PRINCE": {"mentions": 1, "relationships": ["PRINCE"]}, "Cast": {"mentions": 1, "relationships": ["Montague", "Verona", "ho", "Cast"]}, "Aurora": {"mentions": 1, "relationships": ["Aurora", "Away"]}, "Away": {"mentions": 1, "relationships": ["Aurora", "Away"]}, "Ere": {"mentions": 2, "relationships": ["Ere"]}, "Out--": {"mentions": 1, "relationships": ["Out--"]}, "Groan": {"mentions": 1, "relationships": ["Groan"]}, "Dian": {"mentions": 1, "relationships": ["Dian"]}, "Inherit": {"mentions": 1, "relationships": ["Inherit"]}, "Romeo": {"mentions": 19, "relationships": ["Montague", "place,--", "Lies", "Betroth'd", "Benvolio", "Hath", "resort;-- Alack", "Mercutio", "Tybalt", "mar", "Juliet", "Romeo", "Friar John", "Lest"]}, "Shut": {"mentions": 1, "relationships": ["Shut"]}, "County Anselme": {"mentions": 1, "relationships": ["Lucio", "Mercutio", "Valentine", "Livia", "County Anselme"]}, "Mercutio": {"mentions": 18, "relationships": ["Lucio", "Benvolio", "Staying", "Mercutio", "Valentine", "Livia", "Juliet", "Romeo", "kinsman", "County Anselme"]}, "Valentine": {"mentions": 1, "relationships": ["Lucio", "Mercutio", "Valentine", "Livia", "County Anselme"]}, "Livia": {"mentions": 1, "relationships": ["Lucio", "Mercutio", "Valentine", "Livia", "County Anselme"]}, "Lucio": {"mentions": 1, "relationships": ["Lucio", "Mercutio", "Valentine", "Livia", "County Anselme"]}, "ladybird": {"mentions": 1, "relationships": ["God", "ladybird", "Juliet"]}, "God": {"mentions": 2, "relationships": ["God", "ladybird", "Juliet"]}, "Juliet": {"mentions": 43, "relationships": ["Beg", "Madam", "Betroth'd", "Hath", "Juliet", "Verona", "Montagues", "Montague", "Cynthia", "ho", "yon grey", "Tybalt", "Depart", "Friar John", "Thou", "ladybird", "Warm", "Marry", "Romeo", "Arise", "Unfold", "Unseemly", "Romeo Hath", "Mercutio", "God", "kinsman"]}, "JULIET": {"mentions": 12, "relationships": ["JULIET"]}, "Lammas": {"mentions": 2, "relationships": ["Yea", "Susan", "Jule", "Come Lammas-eve", "Lammas"]}, "Come Lammas-eve": {"mentions": 1, "relationships": ["Yea", "Susan", "Jule", "Come Lammas-eve", "Lammas"]}, "Susan": {"mentions": 2, "relationships": ["Yea", "Susan", "Jule", "Come Lammas-eve", "Lammas"]}, "Yea": {"mentions": 1, "relationships": ["Yea", "Susan", "Jule", "Come Lammas-eve", "Lammas"]}, "Jule": {"mentions": 3, "relationships": ["cockerel", "Yea", "Susan", "Jule", "Come Lammas-eve", "Lammas"]}, "cockerel": {"mentions": 1, "relationships": ["cockerel", "Jule"]}, "Marry": {"mentions": 10, "relationships": ["Petrucio", "Madam", "Marry", "Juliet", "Shall"]}, "Find": {"mentions": 1, "relationships": ["Find"]}, "Exit Servant": {"mentions": 1, "relationships": ["Exit Servant"]}, "dun": {"mentions": 1, "relationships": ["ho", "dun"]}, "Queen Mab": {"mentions": 1, "relationships": ["Drawn", "O'er ladies '", "driveth o'er", "Mab", "Athwart", "Queen Mab", "O'er courtiers'", "O'er lawyers'"]}, "Drawn": {"mentions": 1, "relationships": ["Drawn", "O'er ladies '", "driveth o'er", "Mab", "Athwart", "Queen Mab", "O'er courtiers'", "O'er lawyers'"]}, "Athwart": {"mentions": 1, "relationships": ["Drawn", "O'er ladies '", "driveth o'er", "Mab", "Athwart", "Queen Mab", "O'er courtiers'", "O'er lawyers'"]}, "O'er courtiers'": {"mentions": 1, "relationships": ["Drawn", "O'er ladies '", "driveth o'er", "Mab", "Athwart", "Queen Mab", "O'er courtiers'", "O'er lawyers'"]}, "O'er lawyers'": {"mentions": 1, "relationships": ["Drawn", "O'er ladies '", "driveth o'er", "Mab", "Athwart", "Queen Mab", "O'er courtiers'", "O'er lawyers'"]}, "O'er ladies '": {"mentions": 1, "relationships": ["Drawn", "O'er ladies '", "driveth o'er", "Mab", "Athwart", "Queen Mab", "O'er courtiers'", "O'er lawyers'"]}, "Mab": {"mentions": 2, "relationships": ["Drawn", "O'er ladies '", "driveth o'er", "Mab", "Athwart", "Queen Mab", "O'er courtiers'", "O'er lawyers'"]}, "driveth o'er": {"mentions": 1, "relationships": ["Drawn", "O'er ladies '", "driveth o'er", "Mab", "Athwart", "Queen Mab", "O'er courtiers'", "O'er lawyers'"]}, "Begot": {"mentions": 1, "relationships": ["Begot"]}, "Shall": {"mentions": 8, "relationships": ["Shall", "Marry"]}, "Potpan": {"mentions": 1, "relationships": ["Potpan"]}, "Susan Grindstone": {"mentions": 1, "relationships": ["Susan Grindstone"]}, "Capulet": {"mentions": 2, "relationships": ["Capulet"]}, "kinsman": {"mentions": 3, "relationships": ["kinsman", "Mercutio", "Juliet", "earl"]}, "marry": {"mentions": 1, "relationships": ["marry"]}, "Petrucio": {"mentions": 1, "relationships": ["Petrucio", "Marry"]}, "Appear thou": {"mentions": 1, "relationships": ["moveth", "heareth", "Young Adam Cupid", "King Cophetua", "Appear thou", "nick-name", "Venus"]}, "Venus": {"mentions": 2, "relationships": ["moveth", "heareth", "Tybalt", "Young Adam Cupid", "King Cophetua", "Appear thou", "nick-name", "Venus"]}, "nick-name": {"mentions": 1, "relationships": ["moveth", "heareth", "Young Adam Cupid", "King Cophetua", "Appear thou", "nick-name", "Venus"]}, "Young Adam Cupid": {"mentions": 1, "relationships": ["moveth", "heareth", "Young Adam Cupid", "King Cophetua", "Appear thou", "nick-name", "Venus"]}, "King Cophetua": {"mentions": 1, "relationships": ["moveth", "heareth", "Young Adam Cupid", "King Cophetua", "Appear thou", "nick-name", "Venus"]}, "heareth": {"mentions": 1, "relationships": ["moveth", "heareth", "Young Adam Cupid", "King Cophetua", "Appear thou", "nick-name", "Venus"]}, "moveth": {"mentions": 1, "relationships": ["moveth", "heareth", "Young Adam Cupid", "King Cophetua", "Appear thou", "nick-name", "Venus"]}, "Arise": {"mentions": 2, "relationships": ["Arise", "Juliet"]}, "Jove": {"mentions": 1, "relationships": ["Montague", "Thou", "Jove"]}, "Lest": {"mentions": 2, "relationships": ["Lies", "place,--", "Lest", "Tybalt", "Romeo", "resort;-- Alack"]}, "Sweet": {"mentions": 1, "relationships": ["Sweet"]}, "Sweet Montague": {"mentions": 1, "relationships": ["Sweet Montague"]}, "Madam": {"mentions": 5, "relationships": ["Madam", "Marry", "Juliet"]}, "Remembering": {"mentions": 1, "relationships": ["Remembering"]}, "Full": {"mentions": 1, "relationships": ["Full"]}, "Holy Saint Francis": {"mentions": 1, "relationships": ["Jesu Maria", "Lo", "Holy Saint Francis", "Hath"]}, "Jesu Maria": {"mentions": 1, "relationships": ["Jesu Maria", "Lo", "Holy Saint Francis", "Hath"]}, "Hath": {"mentions": 7, "relationships": ["Hath", "Holy Saint Francis", "Lo", "Tybalt", "Depart", "Juliet", "Romeo", "Jesu Maria", "Thou"]}, "Lo": {"mentions": 1, "relationships": ["Jesu Maria", "Lo", "Holy Saint Francis", "Hath"]}, "Tybalt": {"mentions": 15, "relationships": ["Lies", "Beg", "place,--", "Betroth'd", "Hath", "Unseemly", "Lest", "resort;-- Alack", "Tybalt", "Juliet", "Romeo", "Friar John", "Venus"]}, "Jesu": {"mentions": 1, "relationships": ["Jesu"]}, "Petrarch": {"mentions": 1, "relationships": ["Helen", "Laura", "Petrarch", "Cleopatra"]}, "Laura": {"mentions": 1, "relationships": ["Helen", "Laura", "Petrarch", "Cleopatra"]}, "Cleopatra": {"mentions": 1, "relationships": ["Helen", "Laura", "Petrarch", "Cleopatra"]}, "Helen": {"mentions": 1, "relationships": ["Helen", "Laura", "Petrarch", "Cleopatra"]}, "Switch": {"mentions": 1, "relationships": ["Switch"]}, "Peter": {"mentions": 7, "relationships": ["Peter", "Saint Peter's Church"]}, "Good Peter": {"mentions": 1, "relationships": ["Good Peter"]}, "mar": {"mentions": 1, "relationships": ["mar", "Romeo"]}, "Jacks": {"mentions": 1, "relationships": ["Jacks"]}, "Farewell": {"mentions": 2, "relationships": ["Farewell"]}, "Exit PETER": {"mentions": 1, "relationships": ["Exit PETER"]}, "Nay": {"mentions": 1, "relationships": ["Nay"]}, "Henceforward": {"mentions": 2, "relationships": ["Henceforward"]}, "Unfold": {"mentions": 1, "relationships": ["Unfold", "Juliet"]}, "MERCUTIO": {"mentions": 2, "relationships": ["MERCUTIO"]}, "Jack": {"mentions": 2, "relationships": ["Jack"]}, "Capulet,--which": {"mentions": 1, "relationships": ["Capulet,--which"]}, "Gentle Mercutio": {"mentions": 1, "relationships": ["Gentle Mercutio"]}, "Staying": {"mentions": 1, "relationships": ["Staying", "Mercutio"]}, "Shalt": {"mentions": 1, "relationships": ["Shalt", "Thou"]}, "Gallop": {"mentions": 1, "relationships": ["Gallop", "Romeo Leap", "Thou", "Phaethon"]}, "Phaethon": {"mentions": 1, "relationships": ["Gallop", "Romeo Leap", "Thou", "Phaethon"]}, "Romeo Leap": {"mentions": 1, "relationships": ["Gallop", "Romeo Leap", "Thou", "Phaethon"]}, "heartsick groans": {"mentions": 1, "relationships": ["heartsick groans", "Mist"]}, "Mist": {"mentions": 1, "relationships": ["heartsick groans", "Mist"]}, "Lady Juliet": {"mentions": 1, "relationships": ["Lady Juliet"]}, "Unseemly": {"mentions": 1, "relationships": ["Tybalt", "Unseemly", "Beg", "Juliet"]}, "Beg": {"mentions": 1, "relationships": ["Tybalt", "Unseemly", "Beg", "Juliet"]}, "Paris": {"mentions": 2, "relationships": ["Paris", "Acquaint"]}, "Acquaint": {"mentions": 1, "relationships": ["Paris", "Acquaint"]}, "earl": {"mentions": 1, "relationships": ["kinsman", "earl"]}, "yon grey": {"mentions": 1, "relationships": ["Cynthia", "yon grey", "Juliet"]}, "Cynthia": {"mentions": 1, "relationships": ["Cynthia", "yon grey", "Juliet"]}, "Adieu": {"mentions": 1, "relationships": ["Adieu"]}, "Saint Peter's Church": {"mentions": 1, "relationships": ["Peter", "Saint Peter's Church"]}, "Unworthy": {"mentions": 1, "relationships": ["Unworthy"]}, "Proud": {"mentions": 2, "relationships": ["Proud"]}, "Graze": {"mentions": 1, "relationships": ["Graze"]}, "Laurence": {"mentions": 1, "relationships": ["Laurence"]}, "O'er-cover'd": {"mentions": 1, "relationships": ["O'er-cover'd"]}, "Sirrah": {"mentions": 2, "relationships": ["Sirrah"]}, "place,--": {"mentions": 1, "relationships": ["Lies", "place,--", "Lest", "Tybalt", "Romeo", "resort;-- Alack"]}, "Lies": {"mentions": 1, "relationships": ["Lies", "place,--", "Lest", "Tybalt", "Romeo", "resort;-- Alack"]}, "resort;-- Alack": {"mentions": 1, "relationships": ["Lies", "place,--", "Lest", "Tybalt", "Romeo", "resort;-- Alack"]}, "Angelica": {"mentions": 1, "relationships": ["Angelica"]}, "Call Peter": {"mentions": 1, "relationships": ["Call Peter"]}, "merry whoreson": {"mentions": 1, "relationships": ["merry whoreson"]}, "Death": {"mentions": 2, "relationships": ["Death"]}, "PETER": {"mentions": 1, "relationships": ["PETER"]}, "Heart": {"mentions": 1, "relationships": ["Heart"]}, "Simon Catling": {"mentions": 1, "relationships": ["Simon Catling"]}, "James Soundpost": {"mentions": 1, "relationships": ["James Soundpost"]}, "Tush": {"mentions": 1, "relationships": ["Tush"]}, "Mantua": {"mentions": 1, "relationships": ["Mantua"]}, "Contempt": {"mentions": 1, "relationships": ["Contempt"]}, "Suspecting": {"mentions": 1, "relationships": ["Suspecting"]}, "Friar John": {"mentions": 2, "relationships": ["Betroth'd", "Tybalt", "Juliet", "Romeo", "Friar John"]}, "Romeo Hath": {"mentions": 1, "relationships": ["Romeo Hath", "Juliet"]}, "Depart": {"mentions": 1, "relationships": ["Hath", "Depart", "Thou", "Juliet"]}, "Saint Francis": {"mentions": 1, "relationships": ["Saint Francis"]}, "Bliss": {"mentions": 1, "relationships": ["Bliss"]}, "Warm": {"mentions": 1, "relationships": ["Warm", "Juliet"]}, "Betroth'd": {"mentions": 1, "relationships": ["Betroth'd", "Tybalt", "Juliet", "Romeo", "Friar John"]}}